graphblas/__init__.py
graphblas/exceptions.py
graphblas/graphblas.yaml
graphblas/viz.py
graphblas/agg/__init__.py
graphblas/agg/ss.py
graphblas/binary/__init__.py
graphblas/binary/numpy.py
graphblas/binary/ss.py
graphblas/core/__init__.py
graphblas/core/automethods.py
graphblas/core/base.py
graphblas/core/descriptor.py
graphblas/core/dtypes.py
graphblas/core/expr.py
graphblas/core/formatting.py
graphblas/core/infix.py
graphblas/core/infixmethods.py
graphblas/core/mask.py
graphblas/core/matrix.py
graphblas/core/recorder.py
graphblas/core/scalar.py
graphblas/core/slice.py
graphblas/core/utils.py
graphblas/core/vector.py
graphblas/core/operator/__init__.py
graphblas/core/operator/agg.py
graphblas/core/operator/base.py
graphblas/core/operator/binary.py
graphblas/core/operator/indexunary.py
graphblas/core/operator/monoid.py
graphblas/core/operator/select.py
graphblas/core/operator/semiring.py
graphblas/core/operator/unary.py
graphblas/core/operator/utils.py
graphblas/core/ss/__init__.py
graphblas/core/ss/binary.py
graphblas/core/ss/config.py
graphblas/core/ss/context.py
graphblas/core/ss/descriptor.py
graphblas/core/ss/dtypes.py
graphblas/core/ss/indexunary.py
graphblas/core/ss/matrix.py
graphblas/core/ss/prefix_scan.py
graphblas/core/ss/select.py
graphblas/core/ss/unary.py
graphblas/core/ss/vector.py
graphblas/dtypes/__init__.py
graphblas/dtypes/ss.py
graphblas/indexunary/__init__.py
graphblas/indexunary/ss.py
graphblas/io/__init__.py
graphblas/io/_awkward.py
graphblas/io/_matrixmarket.py
graphblas/io/_networkx.py
graphblas/io/_scipy.py
graphblas/io/_sparse.py
graphblas/monoid/__init__.py
graphblas/monoid/numpy.py
graphblas/monoid/ss.py
graphblas/op/__init__.py
graphblas/op/numpy.py
graphblas/op/ss.py
graphblas/select/__init__.py
graphblas/select/ss.py
graphblas/semiring/__init__.py
graphblas/semiring/numpy.py
graphblas/semiring/ss.py
graphblas/ss/__init__.py
graphblas/ss/_core.py
graphblas/tests/__init__.py
graphblas/tests/conftest.py
python_graphblas-2025.2.0.dist-info/LICENSE
python_graphblas-2025.2.0.dist-info/METADATA
python_graphblas-2025.2.0.dist-info/WHEEL
python_graphblas-2025.2.0.dist-info/top_level.txt
python_graphblas-2025.2.0.dist-info/RECORD
