Metadata-Version: 2.2
Name: python-graphblas
Version: 2025.2.0
Summary: Python library for GraphBLAS: high-performance sparse linear algebra for scalable graph analytics
Author: Jim Kitchen, Python-graphblas contributors
Author-email: Erik Welch <erik.n.welch@gmail.com>
Maintainer-email: Erik Welch <erik.n.welch@gmail.com>, Jim Kitchen <jim22k@gmail.com>, Sultan Orazbayev <contact@econpoint.com>
License:                                  Apache License
Project-URL: homepage, https://github.com/python-graphblas/python-graphblas
Project-URL: documentation, https://python-graphblas.readthedocs.io
Project-URL: repository, https://github.com/python-graphblas/python-graphblas
Project-URL: changelog, https://github.com/python-graphblas/python-graphblas/releases
Keywords: graphblas,graph,sparse,matrix,lagraph,suitesparse,Networks,Graph Theory,Mathematics,network,discrete mathematics,math
Classifier: Development Status :: 5 - Production/Stable
Classifier: License :: OSI Approved :: Apache Software License
Classifier: Operating System :: MacOS :: MacOS X
Classifier: Operating System :: POSIX :: Linux
Classifier: Operating System :: Microsoft :: Windows
Classifier: Programming Language :: Python
Classifier: Programming Language :: Python :: 3
Classifier: Programming Language :: Python :: 3.10
Classifier: Programming Language :: Python :: 3.11
Classifier: Programming Language :: Python :: 3.12
Classifier: Programming Language :: Python :: 3.13
Classifier: Programming Language :: Python :: 3 :: Only
Classifier: Intended Audience :: Developers
Classifier: Intended Audience :: Other Audience
Classifier: Intended Audience :: Science/Research
Classifier: Topic :: Scientific/Engineering
Classifier: Topic :: Scientific/Engineering :: Information Analysis
Classifier: Topic :: Scientific/Engineering :: Mathematics
Classifier: Topic :: Software Development :: Libraries :: Python Modules
Requires-Python: >=3.10
License-File: LICENSE
Requires-Dist: numpy>=1.23
Requires-Dist: donfig>=0.6
Requires-Dist: pyyaml>=5.4
Requires-Dist: suitesparse-graphblas<10,>=7.4.0.0
Requires-Dist: numba>=0.55; python_version < "3.14"
Provides-Extra: suitesparse
Requires-Dist: suitesparse-graphblas<10,>=7.4.0.0; extra == "suitesparse"
Provides-Extra: networkx
Requires-Dist: networkx>=2.8; extra == "networkx"
Provides-Extra: numba
Requires-Dist: numba>=0.55; extra == "numba"
Provides-Extra: pandas
Requires-Dist: pandas>=1.5; extra == "pandas"
Provides-Extra: scipy
Requires-Dist: scipy>=1.9; extra == "scipy"
Provides-Extra: suitesparse-udf
Requires-Dist: python-graphblas[numba,suitesparse]; extra == "suitesparse-udf"
Provides-Extra: repr
Requires-Dist: python-graphblas[pandas]; extra == "repr"
Provides-Extra: io
Requires-Dist: python-graphblas[networkx,scipy]; extra == "io"
Requires-Dist: python-graphblas[numba]; python_version < "3.14" and extra == "io"
Requires-Dist: awkward>=2.0; extra == "io"
Requires-Dist: sparse>=0.14; python_version < "3.13" and extra == "io"
Requires-Dist: fast-matrix-market>=1.4.5; python_version < "3.13" and extra == "io"
Provides-Extra: viz
Requires-Dist: python-graphblas[networkx,scipy]; extra == "viz"
Requires-Dist: matplotlib>=3.6; extra == "viz"
Provides-Extra: datashade
Requires-Dist: python-graphblas[numba,pandas,scipy]; extra == "datashade"
Requires-Dist: datashader>=0.14; extra == "datashade"
Requires-Dist: hvplot>=0.8; extra == "datashade"
Provides-Extra: test
Requires-Dist: python-graphblas[pandas,scipy,suitesparse]; extra == "test"
Requires-Dist: packaging>=21; extra == "test"
Requires-Dist: pytest>=6.2; extra == "test"
Requires-Dist: tomli>=1; extra == "test"
Provides-Extra: default
Requires-Dist: python-graphblas[pandas,scipy,suitesparse]; extra == "default"
Requires-Dist: python-graphblas[numba]; python_version < "3.14" and extra == "default"
Provides-Extra: all
Requires-Dist: python-graphblas[default,io,test,viz]; extra == "all"
Requires-Dist: python-graphblas[datashade]; python_version < "3.14" and extra == "all"
